{
 "actions": [],
 "allow_rename": 1,
 "creation": "2024-12-05 09:42:00.428593",
 "default_view": "List",
 "doctype": "DocType",
 "editable_grid": 1,
 "engine": "InnoDB",
 "field_order": [
  "attendance_date",
  "hours_worked",
  "billiable_hours",
  "include_unpaid_breaks",
  "unpaid_breaks_minutes",
  "min_hours_to_include_a_break"
 ],
 "fields": [
  {
   "fieldname": "attendance_date",
   "fieldtype": "Date",
   "in_list_view": 1,
   "label": "Attendance Date"
  },
  {
   "fieldname": "hours_worked",
   "fieldtype": "Float",
   "in_list_view": 1,
   "label": "Hours Worked"
  },
  {
   "fieldname": "billiable_hours",
   "fieldtype": "Float",
   "in_list_view": 1,
   "label": "Billiable Hours",
   "read_only": 1
  },
  {
   "default": "0",
   "fieldname": "include_unpaid_breaks",
   "fieldtype": "Check",
   "label": "Include Unpaid Breaks",
   "read_only": 1
  },
  {
   "fieldname": "unpaid_breaks_minutes",
   "fieldtype": "Float",
   "label": "Unpaid Breaks (Minutes)",
   "read_only": 1
  },
  {
   "fieldname": "min_hours_to_include_a_break",
   "fieldtype": "Float",
   "label": "Min. hours to include a break",
   "read_only": 1
  }
 ],
 "index_web_pages_for_search": 1,
 "istable": 1,
 "links": [],
 "modified": "2024-12-05 09:42:00.428593",
 "modified_by": "Administrator",
 "module": "Nl Attendance Timesheet",
 "name": "Navari Attendance",
 "owner": "Administrator",
 "permissions": [],
 "sort_field": "modified",
 "sort_order": "DESC",
 "states": []
}